<skin name="KrissVGamblersCamo">

	<params>
		<param name="display_name" value="Vector Gamblers Camo"/>
		<param name="description" value="A playing cards camo pattern for the Vector SMG"/>
		<param name="material" value="objects/weapons/kriss_v/kriss_v_playing_cards"/>
	</params>

	<items>
		<item name="KrissV"/>
	</items>

	<steam>
		<param name="tags" value="Category:Skin"/>
		<param name="icon_url" value="http://miscreatedgame.com/shots/item_images/KrissVGamblersCamo_200.png?crc=9679D50C"/>
		<param name="store_hidden" value="0"/>
		<param name="amcoins" value="0"/>
		<param name="tradable" value="1"/>
		<param name="name_color" value="FFFFFF"/>
		<param name="itemdefid" value="200009"/>
		<param name="marketable" value="1"/>
		<param name="store_tags" value="Category:Skin"/>
		<param name="background_color" value="2A2A2A"/>
		<param name="hidden" value="0"/>
		<param name="icon_url_large" value="http://miscreatedgame.com/shots/item_images/KrissVGamblersCamo_2048.png?crc=9679D50C"/>
	</steam>
</skin>